ttmltosrt/__init__.py
ttmltosrt/ttmltosrt.py
ttmltosrt-1.3.0.dist-info/DESCRIPTION.rst
ttmltosrt-1.3.0.dist-info/METADATA
ttmltosrt-1.3.0.dist-info/RECORD
ttmltosrt-1.3.0.dist-info/WHEEL
ttmltosrt-1.3.0.dist-info/entry_points.txt
ttmltosrt-1.3.0.dist-info/metadata.json
ttmltosrt-1.3.0.dist-info/top_level.txt
