Metadata-Version: 2.0
Name: ttmltosrt
Version: 1.3.0
Summary: Convert Timed Text Markup Language to SRT
Home-page: https://github.com/RobbieClarken/ttmltosrt
Author: Robbie Clarken
Author-email: robbie.clarken@gmail.com
License: The MIT License (MIT)
Requires-Dist: beautifulsoup4 (>=4.4.1)
Requires-Dist: click (>=6.2)
